augustus/__init__.py
augustus/__main__.py
augustus/cipher.py
augustus/cli.py
CHANGELOG.md
stepped_augustus-1.2.0.dist-info/entry_points.txt
stepped_augustus-1.2.0.dist-info/LICENSE
stepped_augustus-1.2.0.dist-info/WHEEL
stepped_augustus-1.2.0.dist-info/METADATA
stepped_augustus-1.2.0.dist-info/RECORD
