Metadata-Version: 2.1
Name: stepped-augustus
Version: 1.2.0
Summary: A variation of the Augustus Cipher that offsets space-separated words based on the position of each character.
Home-page: https://github.com/PureFunctor/stepped-augustus
License: MIT
Keywords: augustus,cipher
Author: PureFunctor
Author-email: purefunctor@gmail.com
Requires-Python: >=3.7,<4.0
Classifier: Development Status :: 5 - Production/Stable
Classifier: Environment :: Console
Classifier: License :: OSI Approved :: MIT License
Classifier: Programming Language :: Python :: 3
Classifier: Programming Language :: Python :: 3.7
Classifier: Programming Language :: Python :: 3.8
Classifier: Topic :: Security :: Cryptography
Project-URL: Repository, https://github.com/PureFunctor/stepped-augustus
